{"path":"_news/2021-05-05-diablo-4-will-advance-the-art-of-the-action-rpg-genre-says-activision-blizzard.md","title":"Diablo 4 will “advance the art of the action-RPG genre”, says Activision Blizzard","excerpt":"Activision Blizzard chief operating officer Daniel Alegre mentions that the company feels that Diablo 4 will “advance the art of the action-RPG genre”. Alegre also notes that development on the ...","sourceUrl":"https://smartableai.github.io/diablo4/api/news/2021-05-05-diablo-4-will-advance-the-art-of-the-action-rpg-genre-says-activision-blizzard/index.json","webUrl":"https://www.pcgamesn.com/diablo-4/action-rpg","originalUrl":"https://www.pcgamesn.com/diablo-4/action-rpg","featuredContent":null,"highlight":null,"heat":82,"tags":null,"images":null,"content":"\r\n","type":"article","ampWebUrl":"https://www.pcgamesn.com/diablo-4/action-rpg?amp","cdnAmpWebUrl":"https://www-pcgamesn-com.cdn.ampproject.org/c/s/www.pcgamesn.com/diablo-4/action-rpg?amp","publishedDateTime":"2021-05-05T00:56:00-07:00","updatedDateTime":null,"provider":{"name":"PCGamesN","domain":"pcgamesn.com","images":null,"publishers":null,"authors":null},"locale":"en-us","categories":["news"],"topics":["Diablo 4"]}