{"path":"_news/2022-03-24-blizzard-responds-to-fan-frustration-over-diablo-4-updates.md","title":"Blizzard responds to fan frustration over Diablo 4 updates","excerpt":"The developer of Diablo 4 has acknowledged that blog posts aren't the best way for fans to get a feel for the game. Blizzard will be releasing an update on Diablo's fourth major instalment next week.","sourceUrl":"https://smartableai.github.io/diablo4/api/news/2022-03-24-blizzard-responds-to-fan-frustration-over-diablo-4-updates/index.json","webUrl":"https://www.gamesradar.com/blizzard-responds-to-fan-frustration-over-diablo-4-updates/","originalUrl":"https://www.gamesradar.com/blizzard-responds-to-fan-frustration-over-diablo-4-updates/","featuredContent":null,"highlight":null,"heat":87,"tags":null,"images":[{"url":"https://cdn.mos.cms.futurecdn.net/tkCdQyeFN8DG9gXovvxde6-1200-80.jpg","width":1200,"height":675,"title":null,"attribution":null,"isCached":true}],"content":"\r\n","type":"article","ampWebUrl":null,"cdnAmpWebUrl":null,"publishedDateTime":"2022-03-24T01:15:00-07:00","updatedDateTime":null,"provider":{"name":"GamesRadar","domain":"gamesradar.com","images":null,"publishers":null,"authors":null},"locale":"en-us","categories":["news"],"topics":["Diablo 4"]}