{
  "title": "Games",
  "path": "_games",
  "page": 1,
  "value": [
    {
      "path": "_games/tubegamevideo-diablo-4-33-minutes-of-gameplay-druid-barbarian-sorceress-rogue.md",
      "title": "Diablo 4 - 33 Minutes of Gameplay (Druid, Barbarian, Sorceress, Rogue)",
      "excerpt": "Diablo 4 is an upcoming dungeon crawler action role-playing game developed by Blizzard Entertainment, the fourth title in the Diablo series. The game was ...",
      "sourceUrl": "https://smartableai.github.io/diablo4/api/games/tubegamevideo-diablo-4-33-minutes-of-gameplay-druid-barbarian-sorceress-rogue/index.json",
      "webUrl": "https://smartable.ai/apps/diablo4/game/tubegamevideo-diablo-4-33-minutes-of-gameplay-druid-barbarian-sorceress-rogue/",
      "originalUrl": "https://youtube.com/watch?v=qfeYy1fvUPc",
      "featuredContent": "<iframe width=\"800\" height=\"500\" frameborder=\"0\" src=\"https://www.youtube.com/embed/qfeYy1fvUPc\" allow=\"accelerometer; autoplay; encrypted-media; gyroscope; picture-in-picture\" allowfullscreen></iframe>",
      "length": "PT33M19S",
      "provider": {
        "name": "TubeGameVideo",
        "domain": "youtube.com"
      },
      "topics": [
        "Diablo 4",
        "Druid",
        "Barbarian",
        "Sorceress"
      ],
      "heat": 251,
      "images": [
        {
          "url": "https://i.ytimg.com/vi/qfeYy1fvUPc/maxresdefault.jpg",
          "width": 1280,
          "height": 720,
          "isCached": true
        }
      ],
      "content": "\r\n",
      "type": "video",
      "publishedDateTime": "2021-06-22T07:21:03-07:00"
    },
    {
      "path": "_games/phillip-chu-joy-diablo-iv-blizzcon-2019-demo-barbarian-sorcerer-druid-gameplay-streaming-no-commentary.md",
      "title": "Diablo IV Blizzcon 2019 DEMO – Barbarian, Sorcerer, Druid Gameplay Streaming (No Commentary)",
      "excerpt": "Diablo IV Blizzcon 2019 DEMO – Barbarian, Sorcerer, Druid Gameplay Streaming (No Commentary) Recuerden suscribirse: ...",
      "sourceUrl": "https://smartableai.github.io/diablo4/api/games/phillip-chu-joy-diablo-iv-blizzcon-2019-demo-barbarian-sorcerer-druid-gameplay-streaming-no-commentary/index.json",
      "webUrl": "https://smartable.ai/apps/diablo4/game/phillip-chu-joy-diablo-iv-blizzcon-2019-demo-barbarian-sorcerer-druid-gameplay-streaming-no-commentary/",
      "originalUrl": "https://youtube.com/watch?v=i0CntI1Ez_U",
      "featuredContent": "<iframe width=\"800\" height=\"500\" frameborder=\"0\" src=\"https://www.youtube.com/embed/i0CntI1Ez_U\" allow=\"accelerometer; autoplay; encrypted-media; gyroscope; picture-in-picture\" allowfullscreen></iframe>",
      "length": "PT1H1M50S",
      "provider": {
        "name": "Phillip Chu Joy",
        "domain": "youtube.com"
      },
      "topics": [
        "Diablo 4",
        "Druid",
        "Barbarian"
      ],
      "heat": 85,
      "images": [
        {
          "url": "https://i.ytimg.com/vi/i0CntI1Ez_U/hqdefault.jpg",
          "width": 480,
          "height": 360,
          "isCached": true
        }
      ],
      "content": "\r\n",
      "type": "video",
      "publishedDateTime": "2019-11-03T12:06:38-08:00"
    },
    {
      "path": "_games/rams-play-diablo-iv-druid-gameplay-no-commentary.md",
      "title": "Diablo IV Druid Gameplay . (No Commentary)",
      "excerpt": "The Druid is a savage shapeshifter, fluidly transforming between the forms of a towering bear or a vicious werewolf to fight alongside the creatures of the wild.",
      "sourceUrl": "https://smartableai.github.io/diablo4/api/games/rams-play-diablo-iv-druid-gameplay-no-commentary/index.json",
      "webUrl": "https://smartable.ai/apps/diablo4/game/rams-play-diablo-iv-druid-gameplay-no-commentary/",
      "originalUrl": "https://youtube.com/watch?v=EA13-uAwWp8",
      "featuredContent": "<iframe width=\"800\" height=\"500\" frameborder=\"0\" src=\"https://www.youtube.com/embed/EA13-uAwWp8\" allow=\"accelerometer; autoplay; encrypted-media; gyroscope; picture-in-picture\" allowfullscreen></iframe>",
      "length": "PT21M2S",
      "provider": {
        "name": "Ram's Play",
        "domain": "youtube.com"
      },
      "topics": [
        "Diablo 4",
        "Druid"
      ],
      "heat": 85,
      "images": [
        {
          "url": "https://i.ytimg.com/vi/EA13-uAwWp8/maxresdefault.jpg",
          "width": 1280,
          "height": 720,
          "isCached": true
        }
      ],
      "content": "\r\n",
      "type": "video",
      "publishedDateTime": "2021-01-26T03:13:29-08:00"
    },
    {
      "path": "_games/coolpedia-diablo-4-gameplay-60-fps-all-classes-barbarian-rogue-sorceress-druid-2021.md",
      "title": "Diablo 4 Gameplay 60 FPS All Classes [Barbarian, Rogue, Sorceress & Druid] 2021",
      "excerpt": "Diablo 4 Gameplay 30 minutes video for all classes announced so far by Blizzard. The gameplay video is available in HD 1080p at 60 fps. Which class do you ...",
      "sourceUrl": "https://smartableai.github.io/diablo4/api/games/coolpedia-diablo-4-gameplay-60-fps-all-classes-barbarian-rogue-sorceress-druid-2021/index.json",
      "webUrl": "https://smartable.ai/apps/diablo4/game/coolpedia-diablo-4-gameplay-60-fps-all-classes-barbarian-rogue-sorceress-druid-2021/",
      "originalUrl": "https://youtube.com/watch?v=rg2m2n9HBPo",
      "featuredContent": "<iframe width=\"800\" height=\"500\" frameborder=\"0\" src=\"https://www.youtube.com/embed/rg2m2n9HBPo\" allow=\"accelerometer; autoplay; encrypted-media; gyroscope; picture-in-picture\" allowfullscreen></iframe>",
      "length": "PT28M36S",
      "provider": {
        "name": "Coolpedia",
        "domain": "youtube.com"
      },
      "topics": [
        "Diablo 4",
        "Sorceress",
        "Druid",
        "Barbarian"
      ],
      "heat": 63,
      "images": [
        {
          "url": "https://i.ytimg.com/vi/rg2m2n9HBPo/hqdefault.jpg",
          "width": 480,
          "height": 360,
          "isCached": true
        }
      ],
      "content": "\r\n",
      "type": "video",
      "publishedDateTime": "2021-07-05T14:40:16-07:00"
    },
    {
      "path": "_games/lfp-gaming-diablo-4-gameplay-with-sorceress-barbarian-druid.md",
      "title": "Diablo 4 Gameplay With Sorceress, Barbarian, Druid",
      "excerpt": "1 Hour of Diablo 4 Gameplay With Sorceress, Barbarian and Druid. No commentary, just gameplay, showing the talent tree, skills, UI, enemies and loot that ...",
      "sourceUrl": "https://smartableai.github.io/diablo4/api/games/lfp-gaming-diablo-4-gameplay-with-sorceress-barbarian-druid/index.json",
      "webUrl": "https://smartable.ai/apps/diablo4/game/lfp-gaming-diablo-4-gameplay-with-sorceress-barbarian-druid/",
      "originalUrl": "https://youtube.com/watch?v=Yg2x5IBtT9k",
      "featuredContent": "<iframe width=\"800\" height=\"500\" frameborder=\"0\" src=\"https://www.youtube.com/embed/Yg2x5IBtT9k\" allow=\"accelerometer; autoplay; encrypted-media; gyroscope; picture-in-picture\" allowfullscreen></iframe>",
      "length": "PT1H2M1S",
      "provider": {
        "name": "LFP Gaming",
        "domain": "youtube.com"
      },
      "topics": [
        "Diablo 4",
        "Sorceress",
        "Druid",
        "Barbarian"
      ],
      "heat": 63,
      "images": [
        {
          "url": "https://i.ytimg.com/vi/Yg2x5IBtT9k/maxresdefault.jpg",
          "width": 1280,
          "height": 720,
          "isCached": true
        }
      ],
      "content": "\r\n",
      "type": "video",
      "publishedDateTime": "2019-11-10T01:25:28-08:00"
    },
    {
      "path": "_games/games-world-diablo-4-all-classes-gameplay-barbaro-druida-maga-rouge.md",
      "title": "DIABLO 4 ALL CLASSES - GAMEPLAY - BARBARO - DRUIDA - MAGA -- ROUGE",
      "excerpt": "Diablo IV foi apresentado na blizzcon em 2019 oficialmente, desenvolvido para as plataformas Pc, XboxOne e palystation 4. Bárbaro: 00:00 Maga : 16:34 ...",
      "sourceUrl": "https://smartableai.github.io/diablo4/api/games/games-world-diablo-4-all-classes-gameplay-barbaro-druida-maga-rouge/index.json",
      "webUrl": "https://smartable.ai/apps/diablo4/game/games-world-diablo-4-all-classes-gameplay-barbaro-druida-maga-rouge/",
      "originalUrl": "https://youtube.com/watch?v=EGjC3tzvrWU",
      "featuredContent": "<iframe width=\"800\" height=\"500\" frameborder=\"0\" src=\"https://www.youtube.com/embed/EGjC3tzvrWU\" allow=\"accelerometer; autoplay; encrypted-media; gyroscope; picture-in-picture\" allowfullscreen></iframe>",
      "length": "PT1H5M2S",
      "provider": {
        "name": "Games world",
        "domain": "youtube.com"
      },
      "topics": [
        "Diablo 4",
        "Druid"
      ],
      "heat": 59,
      "images": [
        {
          "url": "https://i.ytimg.com/vi/EGjC3tzvrWU/maxresdefault.jpg",
          "width": 1280,
          "height": 720,
          "isCached": true
        }
      ],
      "content": "\r\n",
      "type": "video",
      "publishedDateTime": "2021-04-28T02:15:14-07:00"
    },
    {
      "path": "_games/game-informer-new-gameplay-today-diablo-ivs-druid.md",
      "title": "New Gameplay Today – Diablo IV's Druid",
      "excerpt": "Ben Reeves joins Jeff Cork and Leo Vader for a look at the third and final announced class for Diablo IV. Head to http://gameinformer.com/blizzard to watch this ...",
      "sourceUrl": "https://smartableai.github.io/diablo4/api/games/game-informer-new-gameplay-today-diablo-ivs-druid/index.json",
      "webUrl": "https://smartable.ai/apps/diablo4/game/game-informer-new-gameplay-today-diablo-ivs-druid/",
      "originalUrl": "https://youtube.com/watch?v=uij9ysBKs4w",
      "featuredContent": "<iframe width=\"800\" height=\"500\" frameborder=\"0\" src=\"https://www.youtube.com/embed/uij9ysBKs4w\" allow=\"accelerometer; autoplay; encrypted-media; gyroscope; picture-in-picture\" allowfullscreen></iframe>",
      "length": "PT20M33S",
      "provider": {
        "name": "Game Informer",
        "domain": "youtube.com"
      },
      "topics": [
        "Diablo 4",
        "Druid"
      ],
      "heat": 56,
      "images": [
        {
          "url": "https://i.ytimg.com/vi/uij9ysBKs4w/maxresdefault.jpg",
          "width": 1280,
          "height": 720,
          "isCached": true
        }
      ],
      "content": "\r\n",
      "type": "video",
      "publishedDateTime": "2019-11-08T06:00:15-08:00"
    },
    {
      "path": "_games/bluddshed-diablo-4-blizzcon-2019-demo-druid-sorceress-barbarian-gameplay.md",
      "title": "Diablo 4 Blizzcon 2019 Demo Druid, Sorceress, Barbarian Gameplay",
      "excerpt": "I was fortunate enough to stream Diablo 4 at Blizzcon 2019, this is the original Gameplay Demo from the showroom floor, enjoy! PODCAST: ...",
      "sourceUrl": "https://smartableai.github.io/diablo4/api/games/bluddshed-diablo-4-blizzcon-2019-demo-druid-sorceress-barbarian-gameplay/index.json",
      "webUrl": "https://smartable.ai/apps/diablo4/game/bluddshed-diablo-4-blizzcon-2019-demo-druid-sorceress-barbarian-gameplay/",
      "originalUrl": "https://youtube.com/watch?v=XKzD1NZwUmw",
      "featuredContent": "<iframe width=\"800\" height=\"500\" frameborder=\"0\" src=\"https://www.youtube.com/embed/XKzD1NZwUmw\" allow=\"accelerometer; autoplay; encrypted-media; gyroscope; picture-in-picture\" allowfullscreen></iframe>",
      "length": "PT1H47M55S",
      "provider": {
        "name": "Bluddshed",
        "domain": "youtube.com"
      },
      "topics": [
        "Diablo 4",
        "Druid",
        "Barbarian",
        "Sorceress"
      ],
      "heat": 55,
      "images": [
        {
          "url": "https://i.ytimg.com/vi/XKzD1NZwUmw/maxresdefault.jpg",
          "width": 1280,
          "height": 720,
          "isCached": true
        }
      ],
      "content": "\r\n",
      "type": "video",
      "publishedDateTime": "2019-11-01T18:15:00-07:00"
    },
    {
      "path": "_games/game-lore-dash-diablo-4-druid-gameplay-trailer-total-breakdown-skills-abilities-locations-items-more.md",
      "title": "Diablo 4: Druid Gameplay Trailer TOTAL BREAKDOWN - Skills, Abilities, Locations, Items & MORE!",
      "excerpt": "If you enjoyed this video please consider subscribing: http://bit.ly/2D9NKHK Diablo Lore Books: https://www.amazon.com/shop/gameloredash?",
      "sourceUrl": "https://smartableai.github.io/diablo4/api/games/game-lore-dash-diablo-4-druid-gameplay-trailer-total-breakdown-skills-abilities-locations-items-more/index.json",
      "webUrl": "https://smartable.ai/apps/diablo4/game/game-lore-dash-diablo-4-druid-gameplay-trailer-total-breakdown-skills-abilities-locations-items-more/",
      "originalUrl": "https://youtube.com/watch?v=RqijCULaS2o",
      "featuredContent": "<iframe width=\"800\" height=\"500\" frameborder=\"0\" src=\"https://www.youtube.com/embed/RqijCULaS2o\" allow=\"accelerometer; autoplay; encrypted-media; gyroscope; picture-in-picture\" allowfullscreen></iframe>",
      "length": "PT13M27S",
      "provider": {
        "name": "Game LORE Dash",
        "domain": "youtube.com"
      },
      "topics": [
        "Diablo 4",
        "Druid"
      ],
      "heat": 51,
      "images": [
        {
          "url": "https://i.ytimg.com/vi/RqijCULaS2o/maxresdefault.jpg",
          "width": 1280,
          "height": 720,
          "isCached": true
        }
      ],
      "content": "\r\n",
      "type": "video",
      "publishedDateTime": "2020-11-09T21:27:21-08:00"
    },
    {
      "path": "_games/gametrailers-diablo-4-barbarian-sorcerer-and-druid-gameplay-trailer.md",
      "title": "Diablo 4 - Barbarian, Sorcerer and Druid Gameplay Trailer",
      "excerpt": "Watch the first gameplay reveal of Diablo 4's three confirmed classes: The Barbarian, the Sorcerer, and the Druid.",
      "sourceUrl": "https://smartableai.github.io/diablo4/api/games/gametrailers-diablo-4-barbarian-sorcerer-and-druid-gameplay-trailer/index.json",
      "webUrl": "https://smartable.ai/apps/diablo4/game/gametrailers-diablo-4-barbarian-sorcerer-and-druid-gameplay-trailer/",
      "originalUrl": "https://youtube.com/watch?v=73Cg4akqTsg",
      "featuredContent": "<iframe width=\"800\" height=\"500\" frameborder=\"0\" src=\"https://www.youtube.com/embed/73Cg4akqTsg\" allow=\"accelerometer; autoplay; encrypted-media; gyroscope; picture-in-picture\" allowfullscreen></iframe>",
      "length": "PT3M3S",
      "provider": {
        "name": "GameTrailers",
        "domain": "youtube.com"
      },
      "topics": [
        "Diablo 4",
        "Druid",
        "Barbarian"
      ],
      "heat": 51,
      "images": [
        {
          "url": "https://i.ytimg.com/vi/73Cg4akqTsg/maxresdefault.jpg",
          "width": 1280,
          "height": 720,
          "isCached": true
        }
      ],
      "content": "\r\n",
      "type": "video",
      "publishedDateTime": "2019-11-01T11:38:31-07:00"
    },
    {
      "path": "_games/giuseppes-gaming-twinfinite-diablo-iv-druid-introduction-and-gameplay-pc-ps4-xbox-one.md",
      "title": "Diablo IV - Druid Introduction and Gameplay [PC, PS4, Xbox One]",
      "excerpt": "Full article: https://twinfinite.net/2019/11/diablo-4-details videos/ Recorded from Blizzcon livestream: https://blizzcon.com/en-us/watch.",
      "sourceUrl": "https://smartableai.github.io/diablo4/api/games/giuseppes-gaming-twinfinite-diablo-iv-druid-introduction-and-gameplay-pc-ps4-xbox-one/index.json",
      "webUrl": "https://smartable.ai/apps/diablo4/game/giuseppes-gaming-twinfinite-diablo-iv-druid-introduction-and-gameplay-pc-ps4-xbox-one/",
      "originalUrl": "https://youtube.com/watch?v=Rp55G6LzuMY",
      "featuredContent": "<iframe width=\"800\" height=\"500\" frameborder=\"0\" src=\"https://www.youtube.com/embed/Rp55G6LzuMY\" allow=\"accelerometer; autoplay; encrypted-media; gyroscope; picture-in-picture\" allowfullscreen></iframe>",
      "length": "PT2M24S",
      "provider": {
        "name": "Giuseppe's Gaming - Twinfinite",
        "domain": "youtube.com"
      },
      "topics": [
        "Diablo 4",
        "Druid"
      ],
      "heat": 51,
      "images": [
        {
          "url": "https://i.ytimg.com/vi/Rp55G6LzuMY/maxresdefault.jpg",
          "width": 1280,
          "height": 720,
          "isCached": true
        }
      ],
      "content": "\r\n",
      "type": "video",
      "publishedDateTime": "2019-11-01T14:30:13-07:00"
    },
    {
      "path": "_games/bajheera-diablo-4-druid-barbarian-gameplay-blizzcon-2019-demo-w-warcraftjen.md",
      "title": "Diablo 4: Druid / Barbarian Gameplay - Blizzcon 2019 Demo w/ Warcraftjen",
      "excerpt": "Twitch - http://www.twitch.tv/bajheera Twitter - https://twitter.com/BajheeraWoW Instagram - https://Instagram.com/BajheeraWoW Facebook ...",
      "sourceUrl": "https://smartableai.github.io/diablo4/api/games/bajheera-diablo-4-druid-barbarian-gameplay-blizzcon-2019-demo-w-warcraftjen/index.json",
      "webUrl": "https://smartable.ai/apps/diablo4/game/bajheera-diablo-4-druid-barbarian-gameplay-blizzcon-2019-demo-w-warcraftjen/",
      "originalUrl": "https://youtube.com/watch?v=5ITKehCJHUk",
      "featuredContent": "<iframe width=\"800\" height=\"500\" frameborder=\"0\" src=\"https://www.youtube.com/embed/5ITKehCJHUk\" allow=\"accelerometer; autoplay; encrypted-media; gyroscope; picture-in-picture\" allowfullscreen></iframe>",
      "length": "PT1H5M28S",
      "provider": {
        "name": "Bajheera",
        "domain": "youtube.com"
      },
      "topics": [
        "Diablo 4",
        "Druid",
        "Barbarian"
      ],
      "heat": 50,
      "images": [
        {
          "url": "https://i.ytimg.com/vi/5ITKehCJHUk/hqdefault.jpg",
          "width": 480,
          "height": 360,
          "isCached": true
        }
      ],
      "content": "\r\n",
      "type": "video",
      "publishedDateTime": "2019-11-06T08:30:33-08:00"
    },
    {
      "path": "_games/bannik13-diablo-4-exclusive-first-look-at-gameplay-for-the-druid-sorceress-and-barbarian-classes.md",
      "title": "DIABLO 4 EXCLUSIVE FIRST LOOK AT GAMEPLAY FOR THE DRUID, SORCERESS AND BARBARIAN CLASSES!",
      "excerpt": "New? Subscribe → https://www.youtube.com/c/bannik13?sub_confirmation=1 Diablo 4 is coming!!!! It is official! Let's check out the exclusive first look at game ...",
      "sourceUrl": "https://smartableai.github.io/diablo4/api/games/bannik13-diablo-4-exclusive-first-look-at-gameplay-for-the-druid-sorceress-and-barbarian-classes/index.json",
      "webUrl": "https://smartable.ai/apps/diablo4/game/bannik13-diablo-4-exclusive-first-look-at-gameplay-for-the-druid-sorceress-and-barbarian-classes/",
      "originalUrl": "https://youtube.com/watch?v=eIhE2Gd7vZc",
      "featuredContent": "<iframe width=\"800\" height=\"500\" frameborder=\"0\" src=\"https://www.youtube.com/embed/eIhE2Gd7vZc\" allow=\"accelerometer; autoplay; encrypted-media; gyroscope; picture-in-picture\" allowfullscreen></iframe>",
      "length": "PT6M48S",
      "provider": {
        "name": "Bannik13",
        "domain": "youtube.com"
      },
      "topics": [
        "Diablo 4",
        "Druid",
        "Sorceress",
        "Barbarian"
      ],
      "heat": 50,
      "images": [
        {
          "url": "https://i.ytimg.com/vi/eIhE2Gd7vZc/maxresdefault.jpg",
          "width": 1280,
          "height": 720,
          "isCached": true
        }
      ],
      "content": "\r\n",
      "type": "video",
      "publishedDateTime": "2019-11-04T18:24:40-08:00"
    },
    {
      "path": "_games/battlegrounds-download-diablo-4-barbarian-sorcerer-and-druid-gameplay.md",
      "title": "Download Diablo 4 Barbarian, Sorcerer and Druid Gameplay",
      "excerpt": "Link Download : http://bit.ly/diablo_4_4 Watch the first gameplay reveal of Diablo 4's three confirmed classes: The Barbarian, the Sorcerer, and the Druid. Diablo ...",
      "sourceUrl": "https://smartableai.github.io/diablo4/api/games/battlegrounds-download-diablo-4-barbarian-sorcerer-and-druid-gameplay/index.json",
      "webUrl": "https://smartable.ai/apps/diablo4/game/battlegrounds-download-diablo-4-barbarian-sorcerer-and-druid-gameplay/",
      "originalUrl": "https://youtube.com/watch?v=QXd_XLzzor4",
      "featuredContent": "<iframe width=\"800\" height=\"500\" frameborder=\"0\" src=\"https://www.youtube.com/embed/QXd_XLzzor4\" allow=\"accelerometer; autoplay; encrypted-media; gyroscope; picture-in-picture\" allowfullscreen></iframe>",
      "length": "PT2M44S",
      "provider": {
        "name": "Battlegrounds",
        "domain": "youtube.com"
      },
      "topics": [
        "Diablo 4",
        "Druid",
        "Barbarian"
      ],
      "heat": 50,
      "images": [
        {
          "url": "https://i.ytimg.com/vi/QXd_XLzzor4/maxresdefault.jpg",
          "width": 1280,
          "height": 720,
          "isCached": true
        }
      ],
      "content": "\r\n",
      "type": "video",
      "publishedDateTime": "2019-11-02T17:29:59-07:00"
    },
    {
      "path": "_games/bluddshed-diablo-4-pvp-rune-words-mythic-items-progression-barbarian-druid-sorceress-blizzcon-2019.md",
      "title": "Diablo 4 Pvp, Rune Words, Mythic Items, Progression, Barbarian, Druid, Sorceress Blizzcon 2019",
      "excerpt": "Welcome to my massive Diablo 4 information station, I spent all weekend playing the demo and talking with developers, hopefully this video helps you out!",
      "sourceUrl": "https://smartableai.github.io/diablo4/api/games/bluddshed-diablo-4-pvp-rune-words-mythic-items-progression-barbarian-druid-sorceress-blizzcon-2019/index.json",
      "webUrl": "https://smartable.ai/apps/diablo4/game/bluddshed-diablo-4-pvp-rune-words-mythic-items-progression-barbarian-druid-sorceress-blizzcon-2019/",
      "originalUrl": "https://youtube.com/watch?v=8qjAiki90cU",
      "featuredContent": "<iframe width=\"800\" height=\"500\" frameborder=\"0\" src=\"https://www.youtube.com/embed/8qjAiki90cU\" allow=\"accelerometer; autoplay; encrypted-media; gyroscope; picture-in-picture\" allowfullscreen></iframe>",
      "length": "PT21M46S",
      "provider": {
        "name": "Bluddshed",
        "domain": "youtube.com"
      },
      "topics": [
        "Diablo 4",
        "Sorceress",
        "Druid",
        "Barbarian"
      ],
      "heat": 50,
      "images": [
        {
          "url": "https://i.ytimg.com/vi/8qjAiki90cU/maxresdefault.jpg",
          "width": 1280,
          "height": 720,
          "isCached": true
        }
      ],
      "content": "\r\n",
      "type": "video",
      "publishedDateTime": "2019-11-02T18:15:15-07:00"
    },
    {
      "path": "_games/coolpedia-diablo-4-gameplay-all-classes-barbarian-rogue-sorceress-druid.md",
      "title": "Diablo 4 Gameplay All Classes [Barbarian, Rogue, Sorceress & Druid]",
      "excerpt": "Diablo 4 Gameplay 30 minutes video for all classes announced so far by Blizzard. The gameplay video is available in HD 1080p at 60 fps. Which class do you ...",
      "sourceUrl": "https://smartableai.github.io/diablo4/api/games/coolpedia-diablo-4-gameplay-all-classes-barbarian-rogue-sorceress-druid/index.json",
      "webUrl": "https://smartable.ai/apps/diablo4/game/coolpedia-diablo-4-gameplay-all-classes-barbarian-rogue-sorceress-druid/",
      "originalUrl": "https://youtube.com/watch?v=rg2m2n9HBPo",
      "featuredContent": "<iframe width=\"800\" height=\"500\" frameborder=\"0\" src=\"https://www.youtube.com/embed/rg2m2n9HBPo\" allow=\"accelerometer; autoplay; encrypted-media; gyroscope; picture-in-picture\" allowfullscreen></iframe>",
      "length": "PT28M36S",
      "provider": {
        "name": "Coolpedia",
        "domain": "youtube.com"
      },
      "topics": [
        "Diablo 4",
        "Druid",
        "Barbarian",
        "Sorceress"
      ],
      "heat": 50,
      "images": [
        {
          "url": "https://i.ytimg.com/vi/rg2m2n9HBPo/maxresdefault.jpg",
          "width": 1280,
          "height": 720,
          "isCached": true
        }
      ],
      "content": "\r\n",
      "type": "video",
      "publishedDateTime": "2021-07-05T14:40:16-07:00"
    },
    {
      "path": "_games/crazygames-diablo-4-new-gameplay-druid-quest-complete.md",
      "title": "DIABLO 4 NEW Gameplay DRUID QUEST COMPLETE",
      "excerpt": "",
      "sourceUrl": "https://smartableai.github.io/diablo4/api/games/crazygames-diablo-4-new-gameplay-druid-quest-complete/index.json",
      "webUrl": "https://smartable.ai/apps/diablo4/game/crazygames-diablo-4-new-gameplay-druid-quest-complete/",
      "originalUrl": "https://youtube.com/watch?v=VtH1862QXaw",
      "featuredContent": "<iframe width=\"800\" height=\"500\" frameborder=\"0\" src=\"https://www.youtube.com/embed/VtH1862QXaw\" allow=\"accelerometer; autoplay; encrypted-media; gyroscope; picture-in-picture\" allowfullscreen></iframe>",
      "length": "PT20M58S",
      "provider": {
        "name": "crazygames",
        "domain": "youtube.com"
      },
      "topics": [
        "Diablo 4",
        "Druid"
      ],
      "heat": 50,
      "images": [
        {
          "url": "https://i.ytimg.com/vi/VtH1862QXaw/maxresdefault.jpg",
          "width": 1280,
          "height": 720,
          "isCached": true
        }
      ],
      "content": "\r\n",
      "type": "video",
      "publishedDateTime": "2020-06-08T14:31:14-07:00"
    },
    {
      "path": "_games/der-ryback-diablo-iv-druide-gameplay-german.md",
      "title": "Diablo IV Druide Gameplay German",
      "excerpt": "",
      "sourceUrl": "https://smartableai.github.io/diablo4/api/games/der-ryback-diablo-iv-druide-gameplay-german/index.json",
      "webUrl": "https://smartable.ai/apps/diablo4/game/der-ryback-diablo-iv-druide-gameplay-german/",
      "originalUrl": "https://youtube.com/watch?v=GfwraRtzWaE",
      "featuredContent": "<iframe width=\"800\" height=\"500\" frameborder=\"0\" src=\"https://www.youtube.com/embed/GfwraRtzWaE\" allow=\"accelerometer; autoplay; encrypted-media; gyroscope; picture-in-picture\" allowfullscreen></iframe>",
      "length": "PT18M10S",
      "provider": {
        "name": "Der Ryback",
        "domain": "youtube.com"
      },
      "topics": [
        "Diablo 4",
        "Druid"
      ],
      "heat": 50,
      "images": [
        {
          "url": "https://i.ytimg.com/vi/GfwraRtzWaE/maxresdefault.jpg",
          "width": 1280,
          "height": 720,
          "isCached": true
        }
      ],
      "content": "\r\n",
      "type": "video",
      "publishedDateTime": "2021-03-04T07:48:20-08:00"
    },
    {
      "path": "_games/game-and-anime-portal-gamer-diablo-4-gameplay-trailer-first-look-at-sorceress-barbarian-and-druid-720p.md",
      "title": "DIABLO 4 Gameplay Trailer First Look at Sorceress, Barbarian and Druid 720p",
      "excerpt": "",
      "sourceUrl": "https://smartableai.github.io/diablo4/api/games/game-and-anime-portal-gamer-diablo-4-gameplay-trailer-first-look-at-sorceress-barbarian-and-druid-720p/index.json",
      "webUrl": "https://smartable.ai/apps/diablo4/game/game-and-anime-portal-gamer-diablo-4-gameplay-trailer-first-look-at-sorceress-barbarian-and-druid-720p/",
      "originalUrl": "https://youtube.com/watch?v=vFnPrLqyjuE",
      "featuredContent": "<iframe width=\"800\" height=\"500\" frameborder=\"0\" src=\"https://www.youtube.com/embed/vFnPrLqyjuE\" allow=\"accelerometer; autoplay; encrypted-media; gyroscope; picture-in-picture\" allowfullscreen></iframe>",
      "length": "PT3M11S",
      "provider": {
        "name": "GAME AND ANIME PORTAL GaMeR",
        "domain": "youtube.com"
      },
      "topics": [
        "Diablo 4",
        "Barbarian",
        "Druid",
        "Sorceress"
      ],
      "heat": 50,
      "images": [
        {
          "url": "https://i.ytimg.com/vi/vFnPrLqyjuE/maxresdefault.jpg",
          "width": 1280,
          "height": 720,
          "isCached": true
        }
      ],
      "content": "\r\n",
      "type": "video",
      "publishedDateTime": "2020-02-16T17:31:17-08:00"
    },
    {
      "path": "_games/he-looks-familiar-diablo-4-official-announcement-cinematic-barbarian-sorcerer-druid-official-gameplay-reaction.md",
      "title": "Diablo 4 - Official Announcement Cinematic & Barbarian, Sorcerer & Druid Official Gameplay Reaction",
      "excerpt": "Diablo 4 - Official Announcement Cinematic & Barbarian, Sorcerer & Druid Official Gameplay Reaction 1.Original:https://youtu.be/0SSYzl9fXOQ 2.",
      "sourceUrl": "https://smartableai.github.io/diablo4/api/games/he-looks-familiar-diablo-4-official-announcement-cinematic-barbarian-sorcerer-druid-official-gameplay-reaction/index.json",
      "webUrl": "https://smartable.ai/apps/diablo4/game/he-looks-familiar-diablo-4-official-announcement-cinematic-barbarian-sorcerer-druid-official-gameplay-reaction/",
      "originalUrl": "https://youtube.com/watch?v=GrdoP_s0snk",
      "featuredContent": "<iframe width=\"800\" height=\"500\" frameborder=\"0\" src=\"https://www.youtube.com/embed/GrdoP_s0snk\" allow=\"accelerometer; autoplay; encrypted-media; gyroscope; picture-in-picture\" allowfullscreen></iframe>",
      "length": "PT13M34S",
      "provider": {
        "name": "He looks Familiar",
        "domain": "youtube.com"
      },
      "topics": [
        "Diablo 4",
        "Barbarian",
        "Druid"
      ],
      "heat": 50,
      "images": [
        {
          "url": "https://i.ytimg.com/vi/GrdoP_s0snk/maxresdefault.jpg",
          "width": 1280,
          "height": 720,
          "isCached": true
        }
      ],
      "content": "\r\n",
      "type": "video",
      "publishedDateTime": "2020-07-22T16:22:01-07:00"
    },
    {
      "path": "_games/imp-diablo-4-druida-todas-as-suas-habilidades-em-pt-br-nao-oficial.md",
      "title": "DIABLO 4 - DRUIDA - TODAS AS SUAS HABILIDADES EM PT-BR - NÃO OFICIAL",
      "excerpt": "Link da Gameplay: https://www.youtube.com/watch?v=uij9ysBKs4w&t=4s Lives nos Canais abaixo, siga pra não perder nenhuma! ⭐ Seja Membro no ...",
      "sourceUrl": "https://smartableai.github.io/diablo4/api/games/imp-diablo-4-druida-todas-as-suas-habilidades-em-pt-br-nao-oficial/index.json",
      "webUrl": "https://smartable.ai/apps/diablo4/game/imp-diablo-4-druida-todas-as-suas-habilidades-em-pt-br-nao-oficial/",
      "originalUrl": "https://youtube.com/watch?v=d2OnR_vcYgU",
      "featuredContent": "<iframe width=\"800\" height=\"500\" frameborder=\"0\" src=\"https://www.youtube.com/embed/d2OnR_vcYgU\" allow=\"accelerometer; autoplay; encrypted-media; gyroscope; picture-in-picture\" allowfullscreen></iframe>",
      "length": "PT25M21S",
      "provider": {
        "name": "Imp",
        "domain": "youtube.com"
      },
      "topics": [
        "Diablo 4",
        "Druid"
      ],
      "heat": 50,
      "images": [
        {
          "url": "https://i.ytimg.com/vi/d2OnR_vcYgU/maxresdefault.jpg",
          "width": 1280,
          "height": 720,
          "isCached": true
        }
      ],
      "content": "\r\n",
      "type": "video",
      "publishedDateTime": "2019-11-13T09:14:24-08:00"
    },
    {
      "path": "_games/kamahl-diablo-4-druid-skills-and-talents.md",
      "title": "Diablo 4 Druid Skills and Talents",
      "excerpt": "What's up guys Kamahl here and today we are going to have an in depth look at the druid talent tree and skills available currently. #Diablo4 #Diablo4Druid ...",
      "sourceUrl": "https://smartableai.github.io/diablo4/api/games/kamahl-diablo-4-druid-skills-and-talents/index.json",
      "webUrl": "https://smartable.ai/apps/diablo4/game/kamahl-diablo-4-druid-skills-and-talents/",
      "originalUrl": "https://youtube.com/watch?v=VHmZp3VlH4k",
      "featuredContent": "<iframe width=\"800\" height=\"500\" frameborder=\"0\" src=\"https://www.youtube.com/embed/VHmZp3VlH4k\" allow=\"accelerometer; autoplay; encrypted-media; gyroscope; picture-in-picture\" allowfullscreen></iframe>",
      "length": "PT19M34S",
      "provider": {
        "name": "Kamahl",
        "domain": "youtube.com"
      },
      "topics": [
        "Diablo 4",
        "Druid"
      ],
      "heat": 50,
      "images": [
        {
          "url": "https://i.ytimg.com/vi/VHmZp3VlH4k/maxresdefault.jpg",
          "width": 1280,
          "height": 720,
          "isCached": true
        }
      ],
      "content": "\r\n",
      "type": "video",
      "publishedDateTime": "2019-11-05T08:51:59-08:00"
    },
    {
      "path": "_games/lzuniy-diablo-4-gameplay-reveal-barbarian-druid-mage-blizzcon-2019.md",
      "title": "DIABLO 4 Gameplay Reveal (Barbarian, Druid, Mage) BlizzCon 2019",
      "excerpt": "DIABLO 4 Gameplay Reveal (Barbarian, Druid, Mage) BlizzCon 2019 SUBSCRIBE → https://goo.gl/wiBNvo subscribe for the latest PS4, Xbox One and PC, ...",
      "sourceUrl": "https://smartableai.github.io/diablo4/api/games/lzuniy-diablo-4-gameplay-reveal-barbarian-druid-mage-blizzcon-2019/index.json",
      "webUrl": "https://smartable.ai/apps/diablo4/game/lzuniy-diablo-4-gameplay-reveal-barbarian-druid-mage-blizzcon-2019/",
      "originalUrl": "https://youtube.com/watch?v=p6zv-Y_masI",
      "featuredContent": "<iframe width=\"800\" height=\"500\" frameborder=\"0\" src=\"https://www.youtube.com/embed/p6zv-Y_masI\" allow=\"accelerometer; autoplay; encrypted-media; gyroscope; picture-in-picture\" allowfullscreen></iframe>",
      "length": "PT2M45S",
      "provider": {
        "name": "lzuniy",
        "domain": "youtube.com"
      },
      "topics": [
        "Diablo 4",
        "Druid",
        "Barbarian"
      ],
      "heat": 50,
      "images": [
        {
          "url": "https://i.ytimg.com/vi/p6zv-Y_masI/maxresdefault.jpg",
          "width": 1280,
          "height": 720,
          "isCached": true
        }
      ],
      "content": "\r\n",
      "type": "video",
      "publishedDateTime": "2019-11-01T11:25:33-07:00"
    },
    {
      "path": "_games/mahariya-gaming-diablo-4-druid-gameplay-no-commentary.md",
      "title": "diablo 4 druid gameplay no commentary",
      "excerpt": "diablo 4 gameplay 2021 sorcerer, diablo 4 gameplay trailer reaction, diablo 4 gameplay trailer reaction mashup, diablo 4 gameplay trailer voice actor, diablo 4 ...",
      "sourceUrl": "https://smartableai.github.io/diablo4/api/games/mahariya-gaming-diablo-4-druid-gameplay-no-commentary/index.json",
      "webUrl": "https://smartable.ai/apps/diablo4/game/mahariya-gaming-diablo-4-druid-gameplay-no-commentary/",
      "originalUrl": "https://youtube.com/watch?v=isAlz5FZAx8",
      "featuredContent": "<iframe width=\"800\" height=\"500\" frameborder=\"0\" src=\"https://www.youtube.com/embed/isAlz5FZAx8\" allow=\"accelerometer; autoplay; encrypted-media; gyroscope; picture-in-picture\" allowfullscreen></iframe>",
      "length": "PT3M52S",
      "provider": {
        "name": "Mahariya gaming",
        "domain": "youtube.com"
      },
      "topics": [
        "Diablo 4",
        "Druid"
      ],
      "heat": 50,
      "images": [
        {
          "url": "https://i.ytimg.com/vi/isAlz5FZAx8/hqdefault.jpg",
          "width": 480,
          "height": 360,
          "isCached": true
        }
      ],
      "content": "\r\n",
      "type": "video",
      "publishedDateTime": "2021-03-10T21:43:43-08:00"
    },
    {
      "path": "_games/online-gaming-tv-channel-diablo-4-gameplay-and-trailer-barbarian-sorcerer-druid.md",
      "title": "DIABLO 4 GAMEPLAY AND TRAILER - BARBARIAN , SORCERER & DRUID",
      "excerpt": "DIABLO 4 GAMEPLAY AND TRAILER - BARBARIAN , SORCERER & DRUID In Diablo IV, we'll be adventuring through Scosglen, the Druid homeland, as Lillith ...",
      "sourceUrl": "https://smartableai.github.io/diablo4/api/games/online-gaming-tv-channel-diablo-4-gameplay-and-trailer-barbarian-sorcerer-druid/index.json",
      "webUrl": "https://smartable.ai/apps/diablo4/game/online-gaming-tv-channel-diablo-4-gameplay-and-trailer-barbarian-sorcerer-druid/",
      "originalUrl": "https://youtube.com/watch?v=IJvA3PPOzUc",
      "featuredContent": "<iframe width=\"800\" height=\"500\" frameborder=\"0\" src=\"https://www.youtube.com/embed/IJvA3PPOzUc\" allow=\"accelerometer; autoplay; encrypted-media; gyroscope; picture-in-picture\" allowfullscreen></iframe>",
      "length": "PT11M33S",
      "provider": {
        "name": "Online-Gaming-TV-Channel",
        "domain": "youtube.com"
      },
      "topics": [
        "Diablo 4",
        "Barbarian",
        "Druid"
      ],
      "heat": 50,
      "images": [
        {
          "url": "https://i.ytimg.com/vi/IJvA3PPOzUc/maxresdefault.jpg",
          "width": 1280,
          "height": 720,
          "isCached": true
        }
      ],
      "content": "\r\n",
      "type": "video",
      "publishedDateTime": "2020-01-05T07:41:20-08:00"
    },
    {
      "path": "_games/osterberg501-diablo-4-announcement-new-diablo-4-gameplay-sorcerer-barbarian-druid-gameplay-blizzcon-2019.md",
      "title": "Diablo 4 ANNOUNCEMENT! New Diablo 4 Gameplay! Sorcerer, Barbarian, & Druid Gameplay! Blizzcon 2019!",
      "excerpt": "Diablo 4 was just announced at Blizzcon 2019, alongside a very good cinematic and some gameplay of the first 3 classes they're showing off. The gameplay ...",
      "sourceUrl": "https://smartableai.github.io/diablo4/api/games/osterberg501-diablo-4-announcement-new-diablo-4-gameplay-sorcerer-barbarian-druid-gameplay-blizzcon-2019/index.json",
      "webUrl": "https://smartable.ai/apps/diablo4/game/osterberg501-diablo-4-announcement-new-diablo-4-gameplay-sorcerer-barbarian-druid-gameplay-blizzcon-2019/",
      "originalUrl": "https://youtube.com/watch?v=kIHwz6Gbkr4",
      "featuredContent": "<iframe width=\"800\" height=\"500\" frameborder=\"0\" src=\"https://www.youtube.com/embed/kIHwz6Gbkr4\" allow=\"accelerometer; autoplay; encrypted-media; gyroscope; picture-in-picture\" allowfullscreen></iframe>",
      "length": "PT3M54S",
      "provider": {
        "name": "Osterberg501",
        "domain": "youtube.com"
      },
      "topics": [
        "Diablo 4",
        "Druid",
        "Barbarian"
      ],
      "heat": 50,
      "images": [
        {
          "url": "https://i.ytimg.com/vi/kIHwz6Gbkr4/maxresdefault.jpg",
          "width": 1280,
          "height": 720,
          "isCached": true
        }
      ],
      "content": "\r\n",
      "type": "video",
      "publishedDateTime": "2019-11-01T12:45:17-07:00"
    },
    {
      "path": "_games/smithtainment-diablo-4-classe-ultimates-barbarian-druid-sorceress-gameplay.md",
      "title": "DIABLO 4 - CLASSE ULTIMATES - BARBARIAN, DRUID, SORCERESS - GAMEPLAY",
      "excerpt": "DIABLO 4 - CLASSE ULTIMATES - BARBARIAN, DRUID, SORCERESS - GAMEPLAY Players will be able to pick from the melee heavy Barbarian, the magic ...",
      "sourceUrl": "https://smartableai.github.io/diablo4/api/games/smithtainment-diablo-4-classe-ultimates-barbarian-druid-sorceress-gameplay/index.json",
      "webUrl": "https://smartable.ai/apps/diablo4/game/smithtainment-diablo-4-classe-ultimates-barbarian-druid-sorceress-gameplay/",
      "originalUrl": "https://youtube.com/watch?v=29d7SJWFajw",
      "featuredContent": "<iframe width=\"800\" height=\"500\" frameborder=\"0\" src=\"https://www.youtube.com/embed/29d7SJWFajw\" allow=\"accelerometer; autoplay; encrypted-media; gyroscope; picture-in-picture\" allowfullscreen></iframe>",
      "length": "PT4M45S",
      "provider": {
        "name": "Smithtainment",
        "domain": "youtube.com"
      },
      "topics": [
        "Diablo 4",
        "Druid",
        "Barbarian",
        "Sorceress"
      ],
      "heat": 50,
      "images": [
        {
          "url": "https://i.ytimg.com/vi/29d7SJWFajw/maxresdefault.jpg",
          "width": 1280,
          "height": 720,
          "isCached": true
        }
      ],
      "content": "\r\n",
      "type": "video",
      "publishedDateTime": "2020-08-12T13:55:08-07:00"
    },
    {
      "path": "_games/smithtainment-diablo-4-druid-compared-to-diablo-2-resurrected-druid-gameplayskills-everything-you-should-know.md",
      "title": "DIABLO 4 DRUID COMPARED TO DIABLO 2 RESURRECTED DRUID - GAMEPLAY/SKILLS - EVERYTHING YOU SHOULD KNOW",
      "excerpt": "DIABLO 4 DRUID COMPARED TO DIABLO 2 RESURRECTED DRUID - GAMEPLAY/SKILLS - EVERYTHING YOU SHOULD KNOW Diablo 4's Druid takes a lot ...",
      "sourceUrl": "https://smartableai.github.io/diablo4/api/games/smithtainment-diablo-4-druid-compared-to-diablo-2-resurrected-druid-gameplayskills-everything-you-should-know/index.json",
      "webUrl": "https://smartable.ai/apps/diablo4/game/smithtainment-diablo-4-druid-compared-to-diablo-2-resurrected-druid-gameplayskills-everything-you-should-know/",
      "originalUrl": "https://youtube.com/watch?v=rZbomhAL-48",
      "featuredContent": "<iframe width=\"800\" height=\"500\" frameborder=\"0\" src=\"https://www.youtube.com/embed/rZbomhAL-48\" allow=\"accelerometer; autoplay; encrypted-media; gyroscope; picture-in-picture\" allowfullscreen></iframe>",
      "length": "PT5M18S",
      "provider": {
        "name": "Smithtainment",
        "domain": "youtube.com"
      },
      "topics": [
        "Diablo 4",
        "Druid"
      ],
      "heat": 50,
      "images": [
        {
          "url": "https://i.ytimg.com/vi/rZbomhAL-48/maxresdefault.jpg",
          "width": 1280,
          "height": 720,
          "isCached": true
        }
      ],
      "content": "\r\n",
      "type": "video",
      "publishedDateTime": "2021-04-08T13:15:48-07:00"
    },
    {
      "path": "_games/smithtainment-new-diablo-4-druid-2020-gameplay-magic-finding-questing.md",
      "title": "*NEW* DIABLO 4 DRUID 2020 GAMEPLAY - MAGIC FINDING & QUESTING",
      "excerpt": "NEW* DIABLO 4 DRUID 2020 GAMEPLAY - MAGIC FINDING & QUESTING The Druid is a savage shapeshifter, fluidly transforming between the forms of a ...",
      "sourceUrl": "https://smartableai.github.io/diablo4/api/games/smithtainment-new-diablo-4-druid-2020-gameplay-magic-finding-questing/index.json",
      "webUrl": "https://smartable.ai/apps/diablo4/game/smithtainment-new-diablo-4-druid-2020-gameplay-magic-finding-questing/",
      "originalUrl": "https://youtube.com/watch?v=-N605UTTviU",
      "featuredContent": "<iframe width=\"800\" height=\"500\" frameborder=\"0\" src=\"https://www.youtube.com/embed/-N605UTTviU\" allow=\"accelerometer; autoplay; encrypted-media; gyroscope; picture-in-picture\" allowfullscreen></iframe>",
      "length": "PT10M21S",
      "provider": {
        "name": "Smithtainment",
        "domain": "youtube.com"
      },
      "topics": [
        "Diablo 4",
        "Druid"
      ],
      "heat": 50,
      "images": [
        {
          "url": "https://i.ytimg.com/vi/-N605UTTviU/maxresdefault.jpg",
          "width": 1280,
          "height": 720,
          "isCached": true
        }
      ],
      "content": "\r\n",
      "type": "video",
      "publishedDateTime": "2020-06-08T17:39:28-07:00"
    },
    {
      "path": "_games/soulnsane-diablo-4-druide-competences-arbre-de-talent.md",
      "title": "DIABLO 4 - Druide: Compétences & Arbre de Talent",
      "excerpt": "Aperçu détaillé des compétences et de l'arbre de talent du Druide. Compétences: https://imgur.com/gallery/IuR7N30 Arbre de Talent: ...",
      "sourceUrl": "https://smartableai.github.io/diablo4/api/games/soulnsane-diablo-4-druide-competences-arbre-de-talent/index.json",
      "webUrl": "https://smartable.ai/apps/diablo4/game/soulnsane-diablo-4-druide-competences-arbre-de-talent/",
      "originalUrl": "https://youtube.com/watch?v=cN41mSCU_dM",
      "featuredContent": "<iframe width=\"800\" height=\"500\" frameborder=\"0\" src=\"https://www.youtube.com/embed/cN41mSCU_dM\" allow=\"accelerometer; autoplay; encrypted-media; gyroscope; picture-in-picture\" allowfullscreen></iframe>",
      "length": "PT11M23S",
      "provider": {
        "name": "Soulnsane",
        "domain": "youtube.com"
      },
      "topics": [
        "Diablo 4",
        "Druid"
      ],
      "heat": 50,
      "images": [
        {
          "url": "https://i.ytimg.com/vi/cN41mSCU_dM/hqdefault.jpg",
          "width": 480,
          "height": 360,
          "isCached": true
        }
      ],
      "content": "\r\n",
      "type": "video",
      "publishedDateTime": "2019-11-11T10:27:28-08:00"
    }
  ],
  "nextPage": 2
}