{"path":"_news/2021-02-20-blizzcon-2021-recap-diablo-2-resurrected-announcement-and-diablo-4-updates.md","title":"Blizzcon 2021 Recap: Diablo 2 Resurrected Announcement and Diablo 4 Updates","excerpt":"Diablo2Resurrected #Diablo4 #DiabloImmortal Sign up for the alpha test here: https://diablo2.blizzard.com/en-us/ ...","sourceUrl":"https://smartableai.github.io/diablo4/api/news/2021-02-20-blizzcon-2021-recap-diablo-2-resurrected-announcement-and-diablo-4-updates/index.json","webUrl":"https://smartable.ai/apps/diablo4/news/2021-02-20-blizzcon-2021-recap-diablo-2-resurrected-announcement-and-diablo-4-updates/","originalUrl":"https://youtube.com/watch?v=-ROl45gQp2M","featuredContent":"<iframe width=\"800\" height=\"500\" frameborder=\"0\" src=\"https://www.youtube.com/embed/-ROl45gQp2M\" allow=\"accelerometer; autoplay; encrypted-media; gyroscope; picture-in-picture\" allowfullscreen></iframe>","highlight":null,"heat":195,"tags":null,"images":[{"url":"https://i.ytimg.com/vi/-ROl45gQp2M/maxresdefault.jpg","width":1280,"height":720,"title":null,"attribution":null,"isCached":true}],"content":"\r\n","type":"video","ampWebUrl":null,"cdnAmpWebUrl":null,"publishedDateTime":"2021-02-19T20:24:37-08:00","updatedDateTime":null,"provider":{"name":"Raxxanterax","domain":"youtube.com","images":null,"publishers":null,"authors":null},"locale":"en-us","categories":["news"],"topics":["Diablo 4"]}